omeka_iiif_uploader/__init__.py
omeka_iiif_uploader/_modidx.py
omeka_iiif_uploader/core.py
omeka_iiif_uploader-0.0.4.dist-info/LICENSE
omeka_iiif_uploader-0.0.4.dist-info/METADATA
omeka_iiif_uploader-0.0.4.dist-info/WHEEL
omeka_iiif_uploader-0.0.4.dist-info/entry_points.txt
omeka_iiif_uploader-0.0.4.dist-info/top_level.txt
omeka_iiif_uploader-0.0.4.dist-info/RECORD
